AUTHORS
COPYING
ChangeLog
MANIFEST.in
ez_setup.py
pylintrc
setup.cfg
setup.py
libturpial/__init__.py
libturpial/config.py
libturpial/exceptions.py
libturpial.egg-info/PKG-INFO
libturpial.egg-info/SOURCES.txt
libturpial.egg-info/dependency_links.txt
libturpial.egg-info/requires.txt
libturpial.egg-info/top_level.txt
libturpial/api/__init__.py
libturpial/api/core.py
libturpial/api/managers/__init__.py
libturpial/api/managers/accountmanager.py
libturpial/api/managers/columnmanager.py
libturpial/api/models/__init__.py
libturpial/api/models/account.py
libturpial/api/models/client.py
libturpial/api/models/column.py
libturpial/api/models/entity.py
libturpial/api/models/list.py
libturpial/api/models/media.py
libturpial/api/models/profile.py
libturpial/api/models/proxy.py
libturpial/api/models/status.py
libturpial/certs/cacert.pem
libturpial/common/__init__.py
libturpial/common/tools.py
libturpial/lib/__init__.py
libturpial/lib/http.py
libturpial/lib/interfaces/__init__.py
libturpial/lib/interfaces/protocol.py
libturpial/lib/interfaces/service.py
libturpial/lib/protocols/__init__.py
libturpial/lib/protocols/identica/__init__.py
libturpial/lib/protocols/identica/identica.py
libturpial/lib/protocols/identica/params.py
libturpial/lib/protocols/twitter/__init__.py
libturpial/lib/protocols/twitter/params.py
libturpial/lib/protocols/twitter/twitter.py
libturpial/lib/services/__init__.py
libturpial/lib/services/media/__init__.py
libturpial/lib/services/media/preview/__init__.py
libturpial/lib/services/media/preview/base.py
libturpial/lib/services/media/preview/flickr.py
libturpial/lib/services/media/preview/imgur.py
libturpial/lib/services/media/preview/lockerz.py
libturpial/lib/services/media/preview/pictwitter.py
libturpial/lib/services/media/preview/twitpic.py
libturpial/lib/services/media/preview/viame.py
libturpial/lib/services/media/preview/yfrog.py
libturpial/lib/services/media/upload/__init__.py
libturpial/lib/services/media/upload/base.py
libturpial/lib/services/media/upload/imgly.py
libturpial/lib/services/media/upload/mobypicture.py
libturpial/lib/services/media/upload/twitgoo.py
libturpial/lib/services/media/upload/twitpic.py
