Metadata-Version: 1.0
Name: libturpial
Version: 1.0
Summary: Microblogging library
Home-page: http://github.com/Turpial/libturpial
Author: Wil Alvarez
Author-email: wil.alejandro@gmail.com
License: GPLv3
Download-URL: http://github.com/Turpial/libturpial
Keywords: twitter identi.ca microblogging api libturpial
Platform: UNKNOWN
Classifier: Development Status :: 5 - Production/Stable
Classifier: Environment :: Console
Classifier: Intended Audience :: Developers
Classifier: License :: OSI Approved :: GNU General Public License (GPL)
Classifier: Operating System :: OS Independent
Classifier: Programming Language :: Python :: 2.7
Classifier: Topic :: Communications
Classifier: Topic :: Internet :: WWW/HTTP
Classifier: Topic :: Software Development :: Libraries :: Python Modules
